observee_logger/__init__.py
observee_logger/configuration.py
observee_logger/constants.py
observee_logger/logging.py
observee_logger/models.py
observee_logger/utils.py
mcp_logger-0.1.23.dist-info/METADATA
mcp_logger-0.1.23.dist-info/WHEEL
mcp_logger-0.1.23.dist-info/RECORD
