Metadata-Version: 2.4
Name: mcp-logger
Version: 0.1.23
Summary: Python SDK for tool usage logging and monitoring
Project-URL: Homepage, https://github.com/observee-ai/python-sdk
Project-URL: Bug Tracker, https://github.com/observee-ai/python-sdk/issues
Author: Observee Team
License-Expression: GPL-3.0-or-later
Requires-Python: >=3.8
Requires-Dist: httpx
Requires-Dist: pydantic
